.DS_Store
dautils/__init__.py
dautils/collect.py
dautils/conf.py
dautils/data.py
dautils/db.py
dautils/log.conf
dautils/log_api.py
dautils/nb.py
dautils/nlp.py
dautils/options.py
dautils/perf.py
dautils/plotting.py
dautils/report.py
dautils/stats.py
dautils/ts.py
dautils/weather.pckl
dautils/web.py
dautils-0.0.2b2.dist-info/LICENSE
dautils-0.0.2b2.dist-info/METADATA
dautils-0.0.2b2.dist-info/WHEEL
dautils-0.0.2b2.dist-info/top_level.txt
dautils-0.0.2b2.dist-info/RECORD
