Metadata-Version: 2.1
Name: dautils
Version: 0.0.2b2
Summary: Data analysis utilities for Python
Home-page: https://www.github.com/diabloxenon/dautils
Author: Naman Bishnoi
Author-email: lucidex@zangetsu.co
License: MIT
Platform: UNKNOWN
Requires-Dist: appdirs
Requires-Dist: landslide
Requires-Dist: pandas-datareader
Requires-Dist: selenium
